[{"country":"Afghanistan","currency":"Afghan Afghani (AFN)"},{"country":"Albania","currency":"Albanian Lek (ALL)"},{"country":"Algeria","currency":"Algerian Dinar (DZD)"},{"country":"Andorra","currency":"Euro (EUR)"},{"country":"Angola","currency":"Angolan Kwanza (AOA)"},{"country":"Antigua and Barbuda","currency":"East Caribbean Dollar (XCD)"},{"country":"Argentina","currency":"Argentine Peso (ARS)"},{"country":"Armenia","currency":"Armenian Dram (AMD)"},{"country":"Australia","currency":"Australian Dollar (AUD)"},{"country":"Austria","currency":"Euro (EUR)"},{"country":"Azerbaijan","currency":"Azerbaijani Manat (AZN)"},{"country":"Bahamas","currency":"Bahamian Dollar (BSD)"},{"country":"Bahrain","currency":"Bahraini Dinar (BHD)"},{"country":"Bangladesh","currency":"Bangladeshi Taka (BDT)"},{"country":"Barbados","currency":"Barbadian Dollar (BBD)"},{"country":"Belarus","currency":"Belarusian Ruble (BYN)"},{"country":"Belgium","currency":"Euro (EUR)"},{"country":"Belize","currency":"Belize Dollar (BZD)"},{"country":"Benin","currency":"West African CFA Franc (XOF)"},{"country":"Bhutan","currency":"Bhutanese Ngultrum (BTN)"},{"country":"Bolivia","currency":"Bolivian Boliviano (BOB)"},{"country":"Bosnia and Herzegovina","currency":"Bosnian Convertible Mark (BAM)"},{"country":"Botswana","currency":"Botswana Pula (BWP)"},{"country":"Brazil","currency":"Brazilian Real (BRL)"},{"country":"Brunei","currency":"Brunei Dollar (BND)"},{"country":"Bulgaria","currency":"Bulgarian Lev (BGN)"},{"country":"Burkina Faso","currency":"West African CFA Franc (XOF)"},{"country":"Burundi","currency":"Burundian Franc (BIF)"},{"country":"Cabo Verde","currency":"Cape Verdean Escudo (CVE)"},{"country":"Cambodia","currency":"Cambodian Riel (KHR)"},{"country":"Cameroon","currency":"Central African CFA Franc (XAF)"},{"country":"Canada","currency":"Canadian Dollar (CAD)"},{"country":"Central African Republic","currency":"Central African CFA Franc (XAF)"},{"country":"Chad","currency":"Central African CFA Franc (XAF)"},{"country":"Chile","currency":"Chilean Peso (CLP)"},{"country":"China","currency":"Chinese Yuan (CNY)"},{"country":"Colombia","currency":"Colombian Peso (COP)"},{"country":"Comoros","currency":"Comorian Franc (KMF)"},{"country":"Congo, Democratic Republic","currency":"Congolese Franc (CDF)"},{"country":"Congo, Republic of","currency":"Central African CFA Franc (XAF)"},{"country":"Costa Rica","currency":"Costa Rican Colón (CRC)"},{"country":"Croatia","currency":"Euro (EUR)"},{"country":"Cuba","currency":"Cuban Peso (CUP)"},{"country":"Cyprus","currency":"Euro (EUR)"},{"country":"Czech Republic","currency":"Czech Koruna (CZK)"},{"country":"Denmark","currency":"Danish Krone (DKK)"},{"country":"Djibouti","currency":"Djiboutian Franc (DJF)"},{"country":"Dominica","currency":"East Caribbean Dollar (XCD)"},{"country":"Dominican Republic","currency":"Dominican Peso (DOP)"},{"country":"Ecuador","currency":"United States Dollar (USD)"},{"country":"Egypt","currency":"Egyptian Pound (EGP)"},{"country":"El Salvador","currency":"United States Dollar (USD)"},{"country":"Equatorial Guinea","currency":"Central African CFA Franc (XAF)"},{"country":"Eritrea","currency":"Eritrean Nakfa (ERN)"},{"country":"Estonia","currency":"Euro (EUR)"},{"country":"Eswatini","currency":"Swazi Lilangeni (SZL)"},{"country":"Ethiopia","currency":"Ethiopian Birr (ETB)"},{"country":"Fiji","currency":"Fijian Dollar (FJD)"},{"country":"Finland","currency":"Euro (EUR)"},{"country":"France","currency":"Euro (EUR)"},{"country":"Gabon","currency":"Central African CFA Franc (XAF)"},{"country":"Gambia","currency":"Gambian Dalasi (GMD)"},{"country":"Georgia","currency":"Georgian Lari (GEL)"},{"country":"Germany","currency":"Euro (EUR)"},{"country":"Ghana","currency":"Ghanaian Cedi (GHS)"},{"country":"Greece","currency":"Euro (EUR)"},{"country":"Grenada","currency":"East Caribbean Dollar (XCD)"},{"country":"Guatemala","currency":"Guatemalan Quetzal (GTQ)"},{"country":"Guinea","currency":"Guinean Franc (GNF)"},{"country":"Guinea-Bissau","currency":"West African CFA Franc (XOF)"},{"country":"Guyana","currency":"Guyanese Dollar (GYD)"},{"country":"Haiti","currency":"Haitian Gourde (HTG)"},{"country":"Honduras","currency":"Honduran Lempira (HNL)"},{"country":"Hungary","currency":"Hungarian Forint (HUF)"},{"country":"Iceland","currency":"Icelandic Króna (ISK)"},{"country":"India","currency":"Indian Rupee (INR)"},{"country":"Indonesia","currency":"Indonesian Rupiah (IDR)"},{"country":"Iran","currency":"Iranian Rial (IRR)"},{"country":"Iraq","currency":"Iraqi Dinar (IQD)"},{"country":"Ireland","currency":"Euro (EUR)"},{"country":"Israel","currency":"Israeli New Shekel (ILS)"},{"country":"Italy","currency":"Euro (EUR)"},{"country":"Jamaica","currency":"Jamaican Dollar (JMD)"},{"country":"Japan","currency":"Japanese Yen (JPY)"},{"country":"Jordan","currency":"Jordanian Dinar (JOD)"},{"country":"Kazakhstan","currency":"Kazakhstani Tenge (KZT)"},{"country":"Kenya","currency":"Kenyan Shilling (KES)"},{"country":"Kiribati","currency":"Australian Dollar (AUD)"},{"country":"Korea, North","currency":"North Korean Won (KPW)"},{"country":"Korea, South","currency":"South Korean Won (KRW)"},{"country":"Kosovo","currency":"Euro (EUR)"},{"country":"Kuwait","currency":"Kuwaiti Dinar (KWD)"},{"country":"Kyrgyzstan","currency":"Kyrgyzstani Som (KGS)"},{"country":"Laos","currency":"Lao Kip (LAK)"},{"country":"Latvia","currency":"Euro (EUR)"},{"country":"Lebanon","currency":"Lebanese Pound (LBP)"},{"country":"Lesotho","currency":"Lesotho Loti (LSL)"},{"country":"Liberia","currency":"Liberian Dollar (LRD)"},{"country":"Libya","currency":"Libyan Dinar (LYD)"},{"country":"Liechtenstein","currency":"Swiss Franc (CHF)"},{"country":"Lithuania","currency":"Euro (EUR)"},{"country":"Luxembourg","currency":"Euro (EUR)"},{"country":"Madagascar","currency":"Malagasy Ariary (MGA)"},{"country":"Malawi","currency":"Malawian Kwacha (MWK)"},{"country":"Malaysia","currency":"Malaysian Ringgit (MYR)"},{"country":"Maldives","currency":"Maldivian Rufiyaa (MVR)"},{"country":"Mali","currency":"West African CFA Franc (XOF)"},{"country":"Malta","currency":"Euro (EUR)"},{"country":"Marshall Islands","currency":"United States Dollar (USD)"},{"country":"Mauritania","currency":"Mauritanian Ouguiya (MRU)"},{"country":"Mauritius","currency":"Mauritian Rupee (MUR)"},{"country":"Mexico","currency":"Mexican Peso (MXN)"},{"country":"Micronesia","currency":"United States Dollar (USD)"},{"country":"Moldova","currency":"Moldovan Leu (MDL)"},{"country":"Monaco","currency":"Euro (EUR)"},{"country":"Mongolia","currency":"Mongolian Tögrög (MNT)"},{"country":"Montenegro","currency":"Euro (EUR)"},{"country":"Morocco","currency":"Moroccan Dirham (MAD)"},{"country":"Mozambique","currency":"Mozambican Metical (MZN)"},{"country":"Myanmar","currency":"Burmese Kyat (MMK)"},{"country":"Namibia","currency":"Namibian Dollar (NAD)"},{"country":"Nauru","currency":"Australian Dollar (AUD)"},{"country":"Nepal","currency":"Nepalese Rupee (NPR)"},{"country":"Netherlands","currency":"Euro (EUR)"},{"country":"New Zealand","currency":"New Zealand Dollar (NZD)"},{"country":"Nicaragua","currency":"Nicaraguan Córdoba (NIO)"},{"country":"Niger","currency":"West African CFA Franc (XOF)"},{"country":"Nigeria","currency":"Nigerian Naira (NGN)"},{"country":"North Macedonia","currency":"Macedonian Denar (MKD)"},{"country":"Norway","currency":"Norwegian Krone (NOK)"},{"country":"Oman","currency":"Omani Rial (OMR)"},{"country":"Pakistan","currency":"Pakistani Rupee (PKR)"},{"country":"Palau","currency":"United States Dollar (USD)"},{"country":"Panama","currency":"Panamanian Balboa (PAB)"},{"country":"Papua New Guinea","currency":"Papua New Guinean Kina (PGK)"},{"country":"Paraguay","currency":"Paraguayan Guarani (PYG)"},{"country":"Peru","currency":"Peruvian Sol (PEN)"},{"country":"Philippines","currency":"Philippine Peso (PHP)"},{"country":"Poland","currency":"Polish Złoty (PLN)"},{"country":"Portugal","currency":"Euro (EUR)"},{"country":"Qatar","currency":"Qatari Riyal (QAR)"},{"country":"Romania","currency":"Romanian Leu (RON)"},{"country":"Russia","currency":"Russian Ruble (RUB)"},{"country":"Rwanda","currency":"Rwandan Franc (RWF)"},{"country":"Saint Kitts and Nevis","currency":"East Caribbean Dollar (XCD)"},{"country":"Saint Lucia","currency":"East Caribbean Dollar (XCD)"},{"country":"Saint Vincent and the Grenadines","currency":"East Caribbean Dollar (XCD)"},{"country":"Samoa","currency":"Samoan Tala (WST)"},{"country":"San Marino","currency":"Euro (EUR)"},{"country":"Sao Tome and Principe","currency":"São Tomé and Príncipe Dobra (STN)"},{"country":"Saudi Arabia","currency":"Saudi Riyal (SAR)"},{"country":"Senegal","currency":"West African CFA Franc (XOF)"},{"country":"Serbia","currency":"Serbian Dinar (RSD)"},{"country":"Seychelles","currency":"Seychellois Rupee (SCR)"},{"country":"Sierra Leone","currency":"Sierra Leonean Leone (S)"},{"country":"Singapore","currency":"Singapore Dollar (SGD)"},{"country":"Slovakia","currency":"Euro (EUR)"},{"country":"Slovenia","currency":"Euro (EUR)"},{"country":"Solomon Islands","currency":"Solomon Islands Dollar (SBD)"},{"country":"Somalia","currency":"Somali Shilling (SOS)"},{"country":"South Africa","currency":"South African Rand (ZAR)"},{"country":"South Sudan","currency":"South Sudanese Pound (SSP)"},{"country":"Spain","currency":"Euro (EUR)"},{"country":"Sri Lanka","currency":"Sri Lankan Rupee (LKR)"},{"country":"Sudan","currency":"Sudanese Pound (SDG)"},{"country":"Suriname","currency":"Surinamese Dollar (SRD)"},{"country":"Sweden","currency":"Swedish Krona (SEK)"},{"country":"Switzerland","currency":"Swiss Franc (CHF)"},{"country":"Syria","currency":"Syrian Pound (SYP)"},{"country":"Taiwan","currency":"New Taiwan Dollar (TWD)"},{"country":"Tajikistan","currency":"Tajikistani Somoni (TJS)"},{"country":"Tanzania","currency":"Tanzanian Shilling (TZS)"},{"country":"Thailand","currency":"Thai Baht (THB)"},{"country":"Timor-Leste","currency":"United States Dollar (USD)"},{"country":"Togo","currency":"West African CFA Franc (XOF)"},{"country":"Tonga","currency":"Tongan Paʻanga (TOP)"},{"country":"Trinidad and Tobago","currency":"Trinidad and Tobago Dollar (TTD)"},{"country":"Tunisia","currency":"Tunisian Dinar (TND)"},{"country":"Turkey","currency":"Turkish Lira (TRY)"},{"country":"Turkmenistan","currency":"Turkmenistani Manat (TMT)"},{"country":"Tuvalu","currency":"Australian Dollar (AUD)"},{"country":"Uganda","currency":"Ugandan Shilling (UGX)"},{"country":"Ukraine","currency":"Ukrainian Hryvnia (UAH)"},{"country":"United Arab Emirates","currency":"UAE Dirham (AED)"},{"country":"United Kingdom","currency":"British Pound (GBP)"},{"country":"United States","currency":"United States Dollar (USD)"},{"country":"Uruguay","currency":"Uruguayan Peso (UYU)"},{"country":"Uzbekistan","currency":"Uzbekistani Som (UZS)"},{"country":"Vanuatu","currency":"Vanuatu Vatu (VUV)"},{"country":"Vatican City","currency":"Euro (EUR)"},{"country":"Venezuela","currency":"Venezuelan Bolívar (VES)"},{"country":"Vietnam","currency":"Vietnamese Đồng (VND)"},{"country":"Yemen","currency":"Yemeni Rial (YER)"},{"country":"Zambia","currency":"Zambian Kwacha (ZMW)"},{"country":"Zimbabwe","currency":"Zimbabwean Dollar (ZWL)"}]
